majamask/__init__.py
majamask/rastermask.py
majamask-1.0.0.dist-info/LICENSE.md
majamask-1.0.0.dist-info/METADATA
majamask-1.0.0.dist-info/WHEEL
majamask-1.0.0.dist-info/entry_points.txt
majamask-1.0.0.dist-info/top_level.txt
majamask-1.0.0.dist-info/RECORD
