Metadata-Version: 2.1
Name: majamask
Version: 1.0.0
Summary: Creates a simplified rastermask from CLM and MG2 masks
Home-page: https://gitlab.orfeo-toolbox.org/maja/maja
Author: CS Group France
Author-email: axelle.pochet@csgroup.eu
License: Apache Version 2
Classifier: Programming Language :: Python :: 3
Classifier: License :: OSI Approved :: Apache Software License
Classifier: Operating System :: POSIX :: Linux
Requires-Python: >=3
License-File: LICENSE.md
Requires-Dist: gdal ==3.4.1
Requires-Dist: numba ==0.56.4
Requires-Dist: Pillow
